deepseek_tan/__init__.py
deepseek_tan-0.1.0.dist-info/METADATA
deepseek_tan-0.1.0.dist-info/WHEEL
deepseek_tan-0.1.0.dist-info/top_level.txt
deepseek_tan-0.1.0.dist-info/RECORD
