Metadata-Version: 2.4
Name: deepseek_tan
Version: 0.1.0
Requires-Python: >=3.8
Requires-Dist: requests
Dynamic: requires-dist
Dynamic: requires-python
